expnumpy/__init__.py
expnumpy/core.py
expnumpy/version.py
expnumpy-0.1.0.dist-info/LICENSE
expnumpy-0.1.0.dist-info/METADATA
expnumpy-0.1.0.dist-info/WHEEL
expnumpy-0.1.0.dist-info/top_level.txt
expnumpy-0.1.0.dist-info/RECORD
